pygenalgo/__init__.py
pygenalgo/engines/__init__.py
pygenalgo/engines/generic_ga.py
pygenalgo/engines/island_model_ga.py
pygenalgo/engines/standard_ga.py
pygenalgo/genome/__init__.py
pygenalgo/genome/chromosome.py
pygenalgo/genome/gene.py
pygenalgo/operators/__init__.py
pygenalgo/operators/genetic_operator.py
pygenalgo/operators/crossover/__init__.py
pygenalgo/operators/crossover/blend_crossover.py
pygenalgo/operators/crossover/crossover_operator.py
pygenalgo/operators/crossover/meta_crossover.py
pygenalgo/operators/crossover/multi_point_crossover.py
pygenalgo/operators/crossover/order_crossover.py
pygenalgo/operators/crossover/partially_mapped_crossover.py
pygenalgo/operators/crossover/position_based_crossover.py
pygenalgo/operators/crossover/single_point_crossover.py
pygenalgo/operators/crossover/uniform_crossover.py
pygenalgo/operators/migration/__init__.py
pygenalgo/operators/migration/clockwise_migration.py
pygenalgo/operators/migration/meta_migration.py
pygenalgo/operators/migration/migration_operator.py
pygenalgo/operators/migration/random_migration.py
pygenalgo/operators/mutation/__init__.py
pygenalgo/operators/mutation/flip_mutator.py
pygenalgo/operators/mutation/gaussian_mutator.py
pygenalgo/operators/mutation/inverse_mutator.py
pygenalgo/operators/mutation/meta_mutator.py
pygenalgo/operators/mutation/mutate_operator.py
pygenalgo/operators/mutation/polynomial_mutator.py
pygenalgo/operators/mutation/random_mutator.py
pygenalgo/operators/mutation/shuffle_mutator.py
pygenalgo/operators/mutation/swap_mutator.py
pygenalgo/operators/selection/__init__.py
pygenalgo/operators/selection/boltzmann_selector.py
pygenalgo/operators/selection/linear_rank_selector.py
pygenalgo/operators/selection/meta_selector.py
pygenalgo/operators/selection/neighborhood_selector.py
pygenalgo/operators/selection/random_selector.py
pygenalgo/operators/selection/roulette_wheel_selector.py
pygenalgo/operators/selection/select_operator.py
pygenalgo-1.9.0.dist-info/LICENSE
pygenalgo-1.9.0.dist-info/METADATA
pygenalgo-1.9.0.dist-info/WHEEL
pygenalgo-1.9.0.dist-info/top_level.txt
pygenalgo-1.9.0.dist-info/RECORD
