Metadata-Version: 2.1
Name: pygenalgo
Version: 1.9.0
Summary: Genetic Algorithms toolbox in Python3
Home-page: https://github.com/vrettasm/PyGeneticAlgorithms
Author: Michalis Vrettas, PhD
Author-email: "Michalis Vrettas, PhD" <michail.vrettas@gmail.com>
License: GPL-3.0
Project-URL: Homepage, https://github.com/vrettasm/PyGeneticAlgorithms
Keywords: optimization,genetic algorithms,island model
Classifier: Programming Language :: Python :: 3
Classifier: Operating System :: OS Independent
Requires-Python: >=3.10
License-File: LICENSE
Requires-Dist: numpy
Requires-Dist: joblib
